.gitignore
MANIFEST.in
README.rst
bootstrap.py
buildout.cfg
setup.py
collective/__init__.py
collective.contentrules.imaging.egg-info/PKG-INFO
collective.contentrules.imaging.egg-info/SOURCES.txt
collective.contentrules.imaging.egg-info/dependency_links.txt
collective.contentrules.imaging.egg-info/entry_points.txt
collective.contentrules.imaging.egg-info/namespace_packages.txt
collective.contentrules.imaging.egg-info/not-zip-safe
collective.contentrules.imaging.egg-info/requires.txt
collective.contentrules.imaging.egg-info/top_level.txt
collective/contentrules/__init__.py
collective/contentrules/imaging/__init__.py
collective/contentrules/imaging/configure.zcml
collective/contentrules/imaging/actions/__init__.py
collective/contentrules/imaging/actions/configure.zcml
collective/contentrules/imaging/actions/scale.py
docs/HISTORY.txt